aswfdocker/__init__.py
aswfdocker/aswfinfo.py
aswfdocker/builder.py
aswfdocker/constants.py
aswfdocker/dockergen.py
aswfdocker/groupinfo.py
aswfdocker/index.py
aswfdocker/migrater.py
aswfdocker/releaser.py
aswfdocker/settings.py
aswfdocker/utils.py
aswfdocker/versioninfo.py
aswfdocker/cli/__init__.py
aswfdocker/cli/aswfdocker.py
aswfdocker/data/__init__.py
aswfdocker/data/ci-image-dockerfile.jinja2
aswfdocker/data/ci-image-readme.jinja2
aswfdocker/data/versions.yaml
aswfdocker/tests/__init__.py
aswfdocker/tests/test_builder.py
aswfdocker/tests/test_dockergen.py
aswfdocker/tests/test_index.py
aswfdocker/tests/test_migrater.py
aswfdocker/tests/test_releaser.py
aswfdocker/tests/test_settings.py
aswfdocker/tests/test_utils.py
aswfdocker-0.7.0.dist-info/LICENSE
aswfdocker-0.7.0.dist-info/METADATA
aswfdocker-0.7.0.dist-info/WHEEL
aswfdocker-0.7.0.dist-info/entry_points.txt
aswfdocker-0.7.0.dist-info/top_level.txt
aswfdocker-0.7.0.dist-info/RECORD
