Metadata-Version: 2.1
Name: aswfdocker
Version: 0.7.0
Summary: ASWF Docker Utilities
Home-page: https://github.com/AcademySoftwareFoundation/aswf-docker
Author: Aloys Baillet
Author-email: aloys.baillet+github@gmail.com
License: Apache License
Classifier: Programming Language :: Python :: 3
Classifier: License :: OSI Approved :: Apache Software License
Classifier: Operating System :: OS Independent
Requires-Python: >=3.6
License-File: LICENSE
Requires-Dist: bottle (==0.12.19)
Requires-Dist: click (==8.1.3)
Requires-Dist: conan (==1.47)
Requires-Dist: importlib-resources (==5.7.1)
Requires-Dist: jinja2 (==3.1.2)
Requires-Dist: node-semver (==0.6.1)
Requires-Dist: patch-ng (==1.17.4)
Requires-Dist: pluginbase (==1.0.1)
Requires-Dist: pygithub (==1.54.1)
Requires-Dist: pyjwt (==1.7.1)
Requires-Dist: pyyaml (==5.4.1)
Requires-Dist: requests (==2.27.1)
Requires-Dist: zipp (==3.8.0) ; python_version < "3.10"
Requires-Dist: python-dateutil (==2.8.2) ; python_version >= "2.7" and python_version not in "3.0, 3.1, 3.2"
Requires-Dist: six (==1.16.0) ; python_version >= "2.7" and python_version not in "3.0, 3.1, 3.2"
Requires-Dist: deprecated (==1.2.13) ; python_version >= "2.7" and python_version not in "3.0, 3.1, 3.2, 3.3"
Requires-Dist: tqdm (==4.64.0) ; python_version >= "2.7" and python_version not in "3.0, 3.1, 3.2, 3.3"
Requires-Dist: colorama (==0.4.4) ; python_version >= "2.7" and python_version not in "3.0, 3.1, 3.2, 3.3, 3.4"
Requires-Dist: wrapt (==1.14.1) ; python_version >= "2.7" and python_version not in "3.0, 3.1, 3.2, 3.3, 3.4"
Requires-Dist: urllib3 (==1.26.9) ; python_version >= "2.7" and python_version not in "3.0, 3.1, 3.2, 3.3, 3.4" and python_version < "4"
Requires-Dist: charset-normalizer (==2.0.12) ; python_version >= "3"
Requires-Dist: idna (==3.3) ; python_version >= "3"
Requires-Dist: certifi (==2022.5.18.1) ; python_version >= "3.6"
Requires-Dist: fasteners (==0.17.3) ; python_version >= "3.6"
Requires-Dist: pygments (==2.12.0) ; python_version >= "3.6"
Requires-Dist: markupsafe (==2.1.1) ; python_version >= "3.7"
Requires-Dist: distro (==1.6.0) ; sys_platform == "linux" or sys_platform == "linux2"
